MediaWorld/__init__.py
MediaWorld/audio/__init__.py
MediaWorld/video/__init__.py
test/__init__.py
MediaWorld-2023.9.1.dist-info/LICENSE.txt
MediaWorld-2023.9.1.dist-info/METADATA
MediaWorld-2023.9.1.dist-info/WHEEL
MediaWorld-2023.9.1.dist-info/top_level.txt
MediaWorld-2023.9.1.dist-info/RECORD
